cocapi/__init__.py
cocapi/api_methods.py
cocapi/async_client.py
cocapi/cache.py
cocapi/client.py
cocapi/cocapi.py
cocapi/config.py
cocapi/metrics.py
cocapi/middleware.py
cocapi/models.py
cocapi/utils.py
cocapi-3.0.1.dist-info/METADATA
cocapi-3.0.1.dist-info/WHEEL
cocapi-3.0.1.dist-info/licenses/LICENSE
cocapi-3.0.1.dist-info/RECORD
