Metadata-Version: 2.4
Name: cocapi
Version: 3.0.1
Summary: A python wrapper around clash of clans api
Project-URL: Homepage, https://github.com/tonybenoy/cocapi
Project-URL: Repository, https://github.com/tonybenoy/cocapi
Project-URL: Issues, https://github.com/tonybenoy/cocapi/issues
Author-email: Tony Benoy <me@tonybenoy.com>
License: GPL-3.0
License-File: LICENSE
Keywords: api,clans,clash,supercell,wrapper
Classifier: Development Status :: 5 - Production/Stable
Classifier: Intended Audience :: Developers
Classifier: License :: OSI Approved :: GNU General Public License v3 (GPLv3)
Classifier: Programming Language :: Python :: 3
Classifier: Programming Language :: Python :: 3.7
Classifier: Programming Language :: Python :: 3.8
Classifier: Programming Language :: Python :: 3.9
Classifier: Programming Language :: Python :: 3.10
Classifier: Programming Language :: Python :: 3.11
Classifier: Programming Language :: Python :: 3.12
Requires-Python: >=3.7.2
Requires-Dist: httpx<1.0.0,>=0.23.0
Provides-Extra: pydantic
Requires-Dist: pydantic>=2.0.0; extra == 'pydantic'
